{
  "parent": "minecraft:recipes/root",
  "criteria": {
    "has_indium_dust": {
      "conditions": {
        "items": [
          {
            "items": "megalosmod:indium_dust"
          }
        ]
      },
      "trigger": "minecraft:inventory_changed"
    },
    "has_the_recipe": {
      "conditions": {
        "recipe": "megalosmod:indium_nugget"
      },
      "trigger": "minecraft:recipe_unlocked"
    }
  },
  "requirements": [
    [
      "has_the_recipe",
      "has_indium_dust"
    ]
  ],
  "rewards": {
    "recipes": [
      "megalosmod:indium_nugget"
    ]
  }
}